mcp_time_server/__init__.py
mcp_time_server/cherry_entry.py
mcp_time_server/cli.py
mcp_time_server/time_server.py
tests/__init__.py
tests/time_server.py
time_server_mcp_cyf-0.1.1.dist-info/licenses/LICENSE
time_server_mcp_cyf-0.1.1.dist-info/METADATA
time_server_mcp_cyf-0.1.1.dist-info/WHEEL
time_server_mcp_cyf-0.1.1.dist-info/entry_points.txt
time_server_mcp_cyf-0.1.1.dist-info/top_level.txt
time_server_mcp_cyf-0.1.1.dist-info/RECORD
